{
  "name": "John Allen",
  "isFemale": false,
  "rank": "",
  "location": "",
  "age": "",
  "stats": [
    {
      "raceDate": "2025-10-17",
      "raceTitle": "Lamaro's Hotel Plate",
      "raceVenue": "Caulfield",
      "raceNumber": 1,
      "raceGrade": "N/A",
      "distance": 1400,
      "horse": "KALEO",
      "trainerName": "Ciaron Maher",
      "spValue": 13,
      "spString": "$13",
      "weight": 57,
      "claimedWeight": null,
      "finishingPosition": 8,
      "barrier": 9,
      "fieldSize": 9,
      "trackType": "Turf",
      "trackCondition": "Good 4",
      "originalFieldSize": 10,
      "scratchedHorses": 1
    },
    {
      "raceDate": "2025-10-17",
      "raceTitle": "Schweppes Ethereal Stakes",
      "raceVenue": "Caulfield",
      "raceNumber": 3,
      "raceGrade": "N/A",
      "distance": 2000,
      "horse": "LUFITAAH",
      "trainerName": "Mitchell Freedman",
      "spValue": 61,
      "spString": "$61",
      "weight": 56,
      "claimedWeight": null,
      "finishingPosition": 12,
      "barrier": 8,
      "fieldSize": 13,
      "trackType": "Turf",
      "trackCondition": "Good 4",
      "originalFieldSize": 13,
      "scratchedHorses": 0
    }
  ],
  "derived": {
    "totalRides": 2,
    "totalWins": 0,
    "totalPlaces": 0,
    "winRate": 0,
    "placeRate": 0,
    "daysSinceLastWin": null,
    "recentForm": "8-X",
    "currentStreak": {
      "type": "losing",
      "count": 2
    }
  }
}