{
  "name": "Ms Amelia Heinrich",
  "isFemale": false,
  "rank": "Apprentice",
  "location": "",
  "age": "",
  "stats": [
    {
      "raceDate": "2025-12-29",
      "raceTitle": "TOPLINE THOROUGHBREDS BENCHMARK 66 HANDICAP",
      "raceVenue": "Murwillumbah",
      "raceState": "NSW",
      "raceNumber": 5,
      "raceGrade": "BenchMark 66, Handicap, Minimum Weight 55kg, Apprentices can claim.",
      "distance": 2020,
      "horse": "TIETAR (NZ)",
      "trainerName": "Matthew Dunn",
      "spValue": 4.8,
      "spString": "$4.80",
      "weight": 59,
      "claimedWeight": 3,
      "finishingPosition": 5,
      "barrier": 4,
      "fieldSize": 8,
      "trackType": "Turf",
      "trackCondition": "Good 4",
      "originalFieldSize": 13,
      "scratchedHorses": 5
    },
    {
      "raceDate": "2025-12-26",
      "raceTitle": "TAB BM 50 HCP",
      "raceVenue": "Ballina",
      "raceState": "NSW",
      "raceNumber": 3,
      "raceGrade": "BenchMark 50, Handicap, Minimum Weight 56kg, Apprentices can claim.",
      "distance": 1015,
      "horse": "SURCOTE",
      "trainerName": "Renita Beaton",
      "spValue": 12,
      "spString": "$12",
      "weight": 57.5,
      "claimedWeight": 3,
      "finishingPosition": 6,
      "barrier": 8,
      "fieldSize": 10,
      "trackType": "Turf",
      "trackCondition": "Good 3",
      "originalFieldSize": 11,
      "scratchedHorses": 1
    },
    {
      "raceDate": "2025-12-26",
      "raceTitle": "BALLINA RSL CLASS 1 & MAIDEN PLATE",
      "raceVenue": "Ballina",
      "raceState": "NSW",
      "raceNumber": 4,
      "raceGrade": "Class 1, Set Weights, Apprentices can claim.",
      "distance": 1605,
      "horse": "SHANNON’S LEGACY",
      "trainerName": "Renita Beaton",
      "spValue": 13,
      "spString": "$13",
      "weight": 54,
      "claimedWeight": 3,
      "finishingPosition": 5,
      "barrier": 6,
      "fieldSize": 8,
      "trackType": "Turf",
      "trackCondition": "Good 3",
      "originalFieldSize": 11,
      "scratchedHorses": 3
    },
    {
      "raceDate": "2025-12-26",
      "raceTitle": "100.9 ZZZFM BOXING DAY CUP BM 50 HCP",
      "raceVenue": "Ballina",
      "raceState": "NSW",
      "raceNumber": 5,
      "raceGrade": "BenchMark 50, Handicap, Minimum Weight 55kg, Apprentices can claim.",
      "distance": 1415,
      "horse": "MA’S EPIC",
      "trainerName": "Renita Beaton",
      "spValue": 6.5,
      "spString": "$6.50",
      "weight": 60.5,
      "claimedWeight": 3,
      "finishingPosition": 4,
      "barrier": 2,
      "fieldSize": 8,
      "trackType": "Turf",
      "trackCondition": "Good 3",
      "originalFieldSize": 12,
      "scratchedHorses": 4
    },
    {
      "raceDate": "2025-12-13",
      "raceTitle": "RESPONSIVE FIRE PROTECTION MAIDEN HANDICAP",
      "raceVenue": "Coffs Harbour",
      "raceState": "NSW",
      "raceNumber": 2,
      "raceGrade": "Maiden, Handicap, Minimum Weight 55.5kg, Apprentices can claim.",
      "distance": 1012,
      "horse": "CHAWYNE",
      "trainerName": "Renita Beaton",
      "spValue": 9,
      "spString": "$9",
      "weight": 53,
      "claimedWeight": 3,
      "finishingPosition": 8,
      "barrier": 8,
      "fieldSize": 8,
      "trackType": "Turf",
      "trackCondition": "Heavy 9",
      "originalFieldSize": 9,
      "scratchedHorses": 1
    },
    {
      "raceDate": "2025-12-13",
      "raceTitle": "THE GOLF CENTRE MAIDEN PLATE",
      "raceVenue": "Coffs Harbour",
      "raceState": "NSW",
      "raceNumber": 3,
      "raceGrade": "Maiden, Set Weights, Apprentices can claim.",
      "distance": 1215,
      "horse": "CHOP CHOP GO",
      "trainerName": "Renita Beaton",
      "spValue": 8.5,
      "spString": "$8.50",
      "weight": 56,
      "claimedWeight": 3,
      "finishingPosition": 6,
      "barrier": 4,
      "fieldSize": 8,
      "trackType": "Turf",
      "trackCondition": "Heavy 9",
      "originalFieldSize": 10,
      "scratchedHorses": 2
    },
    {
      "raceDate": "2025-12-13",
      "raceTitle": "SOUTHSIDE TRUCK CENTRE BENCHMARK 50 HANDICAP",
      "raceVenue": "Coffs Harbour",
      "raceState": "NSW",
      "raceNumber": 4,
      "raceGrade": "BenchMark 50, Handicap, Minimum Weight 55kg, Apprentices can claim.",
      "distance": 1615,
      "horse": "SHANNON’S LEGACY",
      "trainerName": "Renita Beaton",
      "spValue": 12,
      "spString": "$12",
      "weight": 57.5,
      "claimedWeight": 3,
      "finishingPosition": 4,
      "barrier": 5,
      "fieldSize": 9,
      "trackType": "Turf",
      "trackCondition": "Heavy 9",
      "originalFieldSize": 10,
      "scratchedHorses": 1
    },
    {
      "raceDate": "2025-12-13",
      "raceTitle": "WESTPAC RESCUE HELICOPTER SERVICE BENCHMARK 50 HANDICAP",
      "raceVenue": "Coffs Harbour",
      "raceState": "NSW",
      "raceNumber": 5,
      "raceGrade": "BenchMark 50, Handicap, Minimum Weight 55kg, Apprentices can claim.",
      "distance": 1315,
      "horse": "MA’S EPIC",
      "trainerName": "Renita Beaton",
      "spValue": 7,
      "spString": "$7",
      "weight": 60.5,
      "claimedWeight": 3,
      "finishingPosition": 2,
      "barrier": 6,
      "fieldSize": 8,
      "trackType": "Turf",
      "trackCondition": "Heavy 8",
      "originalFieldSize": 10,
      "scratchedHorses": 2
    },
    {
      "raceDate": "2025-12-13",
      "raceTitle": "REG LATTER ELECTRICAL BENCHMARK 50 HANDICAP",
      "raceVenue": "Coffs Harbour",
      "raceState": "NSW",
      "raceNumber": 6,
      "raceGrade": "BenchMark 50, Handicap, Minimum Weight 56kg, Apprentices can claim.",
      "distance": 1012,
      "horse": "SURCOTE",
      "trainerName": "Renita Beaton",
      "spValue": 9,
      "spString": "$9",
      "weight": 57,
      "claimedWeight": 3,
      "finishingPosition": 2,
      "barrier": 6,
      "fieldSize": 10,
      "trackType": "Turf",
      "trackCondition": "Heavy 8",
      "originalFieldSize": 12,
      "scratchedHorses": 2
    },
    {
      "raceDate": "2025-12-12",
      "raceTitle": "RIVERVIEW HOTEL COUNTRY BOOSTED BENCHMARK 58 HANDICAP",
      "raceVenue": "Murwillumbah",
      "raceState": "NSW",
      "raceNumber": 2,
      "raceGrade": "BenchMark 58, Handicap, Minimum Weight 55kg, Apprentices can claim.",
      "distance": 1550,
      "horse": "SHOWMAN (NZ)",
      "trainerName": "Jordan Lee",
      "spValue": 11,
      "spString": "$11",
      "weight": 56.5,
      "claimedWeight": 3,
      "finishingPosition": 3,
      "barrier": 5,
      "fieldSize": 7,
      "trackType": "Turf",
      "trackCondition": "Good 4",
      "originalFieldSize": 9,
      "scratchedHorses": 2
    },
    {
      "raceDate": "2025-12-12",
      "raceTitle": "HERITAGE BROTHERS FUNERAL SERVICES CG&E BENCHMARK 58 HANDICAP",
      "raceVenue": "Murwillumbah",
      "raceState": "NSW",
      "raceNumber": 6,
      "raceGrade": "BenchMark 58, Handicap, Minimum Weight 55kg, Colts, Geldings and Entires, Apprentices can claim.",
      "distance": 1200,
      "horse": "PRESTIGE GUNDY",
      "trainerName": "Jordan Lee",
      "spValue": 7.5,
      "spString": "$7.50",
      "weight": 58,
      "claimedWeight": 3,
      "finishingPosition": 6,
      "barrier": 5,
      "fieldSize": 8,
      "trackType": "Turf",
      "trackCondition": "Good 4",
      "originalFieldSize": 10,
      "scratchedHorses": 2
    },
    {
      "raceDate": "2025-12-12",
      "raceTitle": "TOOHEYS NEW CLASS 1 & MAIDEN PLATE",
      "raceVenue": "Murwillumbah",
      "raceState": "NSW",
      "raceNumber": 8,
      "raceGrade": "Class 1, Set Weights, Apprentices can claim.",
      "distance": 2000,
      "horse": "COSMIC INSANITY",
      "trainerName": "Melissa Birt",
      "spValue": 51,
      "spString": "$51",
      "weight": 54,
      "claimedWeight": 3,
      "finishingPosition": 10,
      "barrier": 8,
      "fieldSize": 10,
      "trackType": "Turf",
      "trackCondition": "Good 4",
      "originalFieldSize": 13,
      "scratchedHorses": 3
    },
    {
      "raceDate": "2025-12-09",
      "raceTitle": "ZZZFM BM 58 HCP",
      "raceVenue": "Ballina",
      "raceState": "NSW",
      "raceNumber": 5,
      "raceGrade": "BenchMark 58, Handicap, Minimum Weight 55kg, Apprentices can claim.",
      "distance": 1900,
      "horse": "BORN TO BE ALIVE",
      "trainerName": "Allan Chau",
      "spValue": 10,
      "spString": "$10",
      "weight": 53.5,
      "claimedWeight": 3,
      "finishingPosition": 2,
      "barrier": 7,
      "fieldSize": 7,
      "trackType": "Turf",
      "trackCondition": "Firm 2",
      "originalFieldSize": 11,
      "scratchedHorses": 4
    },
    {
      "raceDate": "2025-12-09",
      "raceTitle": "FRANGIPANI SKIN & BODY MDN PLT",
      "raceVenue": "Ballina",
      "raceState": "NSW",
      "raceNumber": 6,
      "raceGrade": "Maiden, Set Weights, Apprentices can claim.",
      "distance": 1400,
      "horse": "FLYING SAMMI",
      "trainerName": "Allan Chau",
      "spValue": 151,
      "spString": "$151",
      "weight": 52.5,
      "claimedWeight": 3,
      "finishingPosition": 9,
      "barrier": 8,
      "fieldSize": 9,
      "trackType": "Turf",
      "trackCondition": "Firm 2",
      "originalFieldSize": 15,
      "scratchedHorses": 6
    },
    {
      "raceDate": "2025-12-09",
      "raceTitle": "BALLINA RSL BM 82 HCP",
      "raceVenue": "Ballina",
      "raceState": "NSW",
      "raceNumber": 7,
      "raceGrade": "BenchMark 82, Handicap, Minimum Weight 55kg, Apprentices can claim.",
      "distance": 1300,
      "horse": "DRIALLE",
      "trainerName": "Renita Beaton",
      "spValue": 5.5,
      "spString": "$5.50",
      "weight": 52,
      "claimedWeight": 3,
      "finishingPosition": 3,
      "barrier": 4,
      "fieldSize": 7,
      "trackType": "Turf",
      "trackCondition": "Firm 2",
      "originalFieldSize": 14,
      "scratchedHorses": 7
    }
  ],
  "derived": {
    "totalRides": 15,
    "totalWins": 0,
    "totalPlaces": 5,
    "winRate": 0,
    "placeRate": 0.33,
    "daysSinceLastWin": null,
    "recentForm": "2-6-5-4-5",
    "currentStreak": {
      "type": "losing",
      "count": 15
    }
  }
}
