{
  "name": "Ms Liberty Smyth",
  "isFemale": false,
  "rank": "Apprentice",
  "location": "",
  "age": "",
  "stats": [
    {
      "raceDate": "2026-01-06",
      "raceTitle": "TACKING POINT TAVERN MAIDEN PLATE",
      "raceVenue": "Port Macquarie",
      "raceState": "NSW",
      "raceNumber": 1,
      "raceGrade": "Maiden, Set Weights, Apprentices can claim.",
      "distance": 1500,
      "horse": "DWAYNE",
      "trainerName": "Nathan Doyle",
      "spValue": 1.75,
      "spString": "$1.75F",
      "weight": 55,
      "claimedWeight": 4,
      "finishingPosition": 1,
      "barrier": 7,
      "fieldSize": 7,
      "trackType": "Turf",
      "trackCondition": "Good 4",
      "originalFieldSize": 8,
      "scratchedHorses": 1
    },
    {
      "raceDate": "2026-01-01",
      "raceTitle": "HARELEC OFFGRID BENCHMARK 50 HANDICAP",
      "raceVenue": "Port Macquarie",
      "raceState": "NSW",
      "raceNumber": 3,
      "raceGrade": "BenchMark 50, Handicap, Minimum Weight 56kg, Apprentices can claim.",
      "distance": 1108,
      "horse": "YES YES BOSS",
      "trainerName": "Carlos Antonio",
      "spValue": 12,
      "spString": "$12",
      "weight": 55,
      "claimedWeight": 4,
      "finishingPosition": 5,
      "barrier": 4,
      "fieldSize": 8,
      "trackType": "Turf",
      "trackCondition": "Good 4",
      "originalFieldSize": 9,
      "scratchedHorses": 1
    },
    {
      "raceDate": "2026-01-01",
      "raceTitle": "PRM SWITCHBOARDS MAIDEN PLATE",
      "raceVenue": "Port Macquarie",
      "raceState": "NSW",
      "raceNumber": 4,
      "raceGrade": "Maiden, Set Weights, Apprentices can claim.",
      "distance": 1108,
      "horse": "NAMARA (NZ)",
      "trainerName": "Kris Lees",
      "spValue": 3.3,
      "spString": "$3.30F",
      "weight": 53,
      "claimedWeight": 4,
      "finishingPosition": 4,
      "barrier": 4,
      "fieldSize": 8,
      "trackType": "Turf",
      "trackCondition": "Good 4",
      "originalFieldSize": 10,
      "scratchedHorses": 2
    },
    {
      "raceDate": "2026-01-01",
      "raceTitle": "HARELEC SOLAR SERVICES BENCHMARK 50 HANDICAP",
      "raceVenue": "Port Macquarie",
      "raceState": "NSW",
      "raceNumber": 5,
      "raceGrade": "BenchMark 50, Handicap, Minimum Weight 55kg, Apprentices can claim.",
      "distance": 1208,
      "horse": "GOLDEN COW",
      "trainerName": "Carlos Antonio",
      "spValue": 16,
      "spString": "$16",
      "weight": 56.5,
      "claimedWeight": 4,
      "finishingPosition": 9,
      "barrier": 5,
      "fieldSize": 9,
      "trackType": "Turf",
      "trackCondition": "Good 4",
      "originalFieldSize": 12,
      "scratchedHorses": 3
    },
    {
      "raceDate": "2026-01-01",
      "raceTitle": "HARELEC SOLAR POWER SPECIALISTS BENCHMARK 50 HANDICAP",
      "raceVenue": "Port Macquarie",
      "raceState": "NSW",
      "raceNumber": 6,
      "raceGrade": "BenchMark 50, Handicap, Minimum Weight 55kg, Apprentices can claim.",
      "distance": 1512,
      "horse": "DAYU",
      "trainerName": "Carlos Antonio",
      "spValue": 10,
      "spString": "$10",
      "weight": 52.5,
      "claimedWeight": 4,
      "finishingPosition": 9,
      "barrier": 4,
      "fieldSize": 9,
      "trackType": "Turf",
      "trackCondition": "Good 4",
      "originalFieldSize": 10,
      "scratchedHorses": 1
    },
    {
      "raceDate": "2025-12-27",
      "raceTitle": "TAB VENUE MODE MAIDEN PLATE",
      "raceVenue": "Coffs Harbour",
      "raceState": "NSW",
      "raceNumber": 5,
      "raceGrade": "Maiden, Set Weights, Apprentices can claim.",
      "distance": 1200,
      "horse": "ANTILOPINI",
      "trainerName": "Kris Lees",
      "spValue": 4.6,
      "spString": "$4.60",
      "weight": 51.5,
      "claimedWeight": 4,
      "finishingPosition": 4,
      "barrier": 4,
      "fieldSize": 8,
      "trackType": "Turf",
      "trackCondition": "Heavy 10",
      "originalFieldSize": 14,
      "scratchedHorses": 6
    }
  ],
  "derived": {
    "totalRides": 6,
    "totalWins": 1,
    "totalPlaces": 1,
    "winRate": 0.17,
    "placeRate": 0.17,
    "daysSinceLastWin": 2,
    "recentForm": "5-4-9-9-1",
    "currentStreak": {
      "type": "win",
      "count": 1
    }
  }
}
